openkitx403_agent/__init__.py
openkitx403_agent/agent.py
openkitx403_agent/langchain_tool.py
openkitx403_agent/types.py
openkitx403_agent-1.0.0.dist-info/METADATA
openkitx403_agent-1.0.0.dist-info/WHEEL
openkitx403_agent-1.0.0.dist-info/RECORD
