Metadata-Version: 2.4
Name: openkitx403-agent
Version: 1.0.0
Summary: AI Agent toolkit for OpenKitx403 Solana wallet authentication
License: MIT
Keywords: solana,blockchain,wallet,authentication,ai,agent,langchain,web3
Author: OpenKitx403
Author-email: support@openkitx403.dev
Requires-Python: >=3.8,<4.0
Classifier: Development Status :: 5 - Production/Stable
Classifier: Intended Audience :: Developers
Classifier: License :: OSI Approved :: MIT License
Classifier: Programming Language :: Python :: 3
Classifier: Programming Language :: Python :: 3.8
Classifier: Programming Language :: Python :: 3.9
Classifier: Programming Language :: Python :: 3.10
Classifier: Programming Language :: Python :: 3.11
Classifier: Programming Language :: Python :: 3.12
Classifier: Programming Language :: Python :: 3.13
Classifier: Programming Language :: Python :: 3.14
Classifier: Topic :: Security :: Cryptography
Classifier: Topic :: Software Development :: Libraries :: Python Modules
Provides-Extra: langchain
Requires-Dist: httpx (>=0.24.0,<0.25.0)
Requires-Dist: openkitx403-client (>=0.1.5,<0.2.0)
Requires-Dist: pydantic (>=2.0.0,<3.0.0)
Project-URL: Bug Tracker, https://github.com/openkitx403/openkitx403/issues
Project-URL: Changelog, https://github.com/openkitx403/openkitx403/blob/main/CHANGELOG.md
Project-URL: Documentation, https://openkitx403.dev/docs
Project-URL: Homepage, https://openkitx403.dev
Project-URL: Repository, https://github.com/openkitx403/openkitx403
